mlkernels/__init__.py
mlkernels/_version.py
mlkernels/autograd.py
mlkernels/jax.py
mlkernels/kernel.py
mlkernels/mean.py
mlkernels/meanvar.py
mlkernels/tensorflow.py
mlkernels/torch.py
mlkernels/util.py
mlkernels/kernels/__init__.py
mlkernels/kernels/ceq.py
mlkernels/kernels/decaying.py
mlkernels/kernels/delta.py
mlkernels/kernels/derivative.py
mlkernels/kernels/eq.py
mlkernels/kernels/linear.py
mlkernels/kernels/log.py
mlkernels/kernels/matern12.py
mlkernels/kernels/matern32.py
mlkernels/kernels/matern52.py
mlkernels/kernels/one.py
mlkernels/kernels/periodic.py
mlkernels/kernels/posterior.py
mlkernels/kernels/product.py
mlkernels/kernels/reverse.py
mlkernels/kernels/rq.py
mlkernels/kernels/scaled.py
mlkernels/kernels/selected.py
mlkernels/kernels/shifted.py
mlkernels/kernels/stretched.py
mlkernels/kernels/subspace.py
mlkernels/kernels/sum.py
mlkernels/kernels/tensor.py
mlkernels/kernels/transformed.py
mlkernels/kernels/zero.py
mlkernels/means/__init__.py
mlkernels/means/derivative.py
mlkernels/means/one.py
mlkernels/means/posterior.py
mlkernels/means/product.py
mlkernels/means/scaled.py
mlkernels/means/selected.py
mlkernels/means/shifted.py
mlkernels/means/stretched.py
mlkernels/means/sum.py
mlkernels/means/tensor.py
mlkernels/means/transformed.py
mlkernels/means/zero.py
tests/__init__.py
tests/test_boxing.py
tests/test_kernel.py
tests/test_mean.py
tests/test_mean_var.py
tests/util.py
tests/util_mean.py
tests/kernels/__init__.py
tests/kernels/test_ceq.py
tests/kernels/test_decaying.py
tests/kernels/test_delta.py
tests/kernels/test_derivative.py
tests/kernels/test_eq.py
tests/kernels/test_linear.py
tests/kernels/test_log.py
tests/kernels/test_matern12.py
tests/kernels/test_matern32.py
tests/kernels/test_matern52.py
tests/kernels/test_one.py
tests/kernels/test_periodic.py
tests/kernels/test_posterior.py
tests/kernels/test_product.py
tests/kernels/test_reverse.py
tests/kernels/test_rq.py
tests/kernels/test_scaled.py
tests/kernels/test_selected.py
mlkernels-0.4.0.dist-info/LICENCE.txt
mlkernels-0.4.0.dist-info/METADATA
mlkernels-0.4.0.dist-info/WHEEL
mlkernels-0.4.0.dist-info/top_level.txt
mlkernels-0.4.0.dist-info/RECORD
