Metadata-Version: 2.1
Name: mlkernels
Version: 0.4.0
Summary: Kernels, the machine learning ones
Home-page: https://github.com/wesselb/mlkernels
Author: Wessel Bruinsma
Author-email: wessel.p.bruinsma@gmail.com
License: MIT
Requires-Python: >=3.6
License-File: LICENCE.txt
Requires-Dist: numpy (>=1.16)
Requires-Dist: algebra (>=1.2)
Requires-Dist: backends (>=1.4.11)
Requires-Dist: backends-matrix (>=1.2.1)
Requires-Dist: plum-dispatch (>=2)
